flower/__init__.py
flower/events.py
flower/exceptions.py
flower/models.py
flower/options.py
flower/urls.py
flower/api/__init__.py
flower/api/control.py
flower/api/events.py
flower/api/tasks.py
flower/api/workers.py
flower/management/__init__.py
flower/management/commands/__init__.py
flower/management/commands/flower_events.py
flower/static/flower/favicon.ico
flower/static/flower/swagger.json
flower/static/flower/css/bootstrap-datetimepicker.min.css
flower/static/flower/css/bootstrap-responsive.css
flower/static/flower/css/bootstrap-responsive.min.css
flower/static/flower/css/bootstrap.css
flower/static/flower/css/bootstrap.min.css
flower/static/flower/css/flower.css
flower/static/flower/css/jquery-ui.css
flower/static/flower/css/jquery.dataTables.buttons.min.css
flower/static/flower/css/jquery.dataTables.colReorder.min.css
flower/static/flower/css/jquery.dataTables.css
flower/static/flower/css/jquery.dataTables.min.css
flower/static/flower/css/jquery.dataTables.select.min.css
flower/static/flower/css/rickshaw.min.css
flower/static/flower/css/images/ui-bg_flat_0_aaaaaa_40x100.png
flower/static/flower/css/images/ui-bg_flat_75_ffffff_40x100.png
flower/static/flower/css/images/ui-bg_glass_55_fbf9ee_1x400.png
flower/static/flower/css/images/ui-bg_glass_65_ffffff_1x400.png
flower/static/flower/css/images/ui-bg_glass_75_dadada_1x400.png
flower/static/flower/css/images/ui-bg_glass_75_e6e6e6_1x400.png
flower/static/flower/css/images/ui-bg_glass_95_fef1ec_1x400.png
flower/static/flower/css/images/ui-bg_highlight-soft_75_cccccc_1x100.png
flower/static/flower/css/images/ui-icons_222222_256x240.png
flower/static/flower/css/images/ui-icons_2e83ff_256x240.png
flower/static/flower/css/images/ui-icons_454545_256x240.png
flower/static/flower/css/images/ui-icons_888888_256x240.png
flower/static/flower/css/images/ui-icons_cd0a0a_256x240.png
flower/static/flower/img/apple-touch-icon-114-precomposed.png
flower/static/flower/img/apple-touch-icon-144-precomposed.png
django_flower-1.0.0.dist-info/LICENSE
django_flower-1.0.0.dist-info/METADATA
django_flower-1.0.0.dist-info/WHEEL
django_flower-1.0.0.dist-info/top_level.txt
django_flower-1.0.0.dist-info/RECORD
